Lib/__init__.py
Lib/Api/__init__.py
Lib/Api/yly_express_print.py
Lib/Api/yly_oauth.py
Lib/Api/yly_picture_print.py
Lib/Api/yly_print.py
Lib/Api/yly_print_menu.py
Lib/Api/yly_printer.py
Lib/Config/__init__.py
Lib/Config/config.py
Lib/Oauth/__init__.py
Lib/Oauth/oauth.py
Lib/Protocol/__init__.py
Lib/Protocol/rpc_client.py
yly_python_sdk-2.0.4.dist-info/METADATA
yly_python_sdk-2.0.4.dist-info/WHEEL
yly_python_sdk-2.0.4.dist-info/top_level.txt
yly_python_sdk-2.0.4.dist-info/RECORD
