Metadata-Version: 2.1
Name: yly-python-sdk
Version: 2.0.4
Summary: yly openapi python sdk
Home-page: UNKNOWN
Author: 曲子陌
Author-email: lwy@yilianyun.net
License: MIT Licence
Keywords: python,openapi
Platform: UNKNOWN
